setup.cfg
setup.py
lrn_click/__init__.py
lrn_click.egg-info/PKG-INFO
lrn_click.egg-info/SOURCES.txt
lrn_click.egg-info/dependency_links.txt
lrn_click.egg-info/requires.txt
lrn_click.egg-info/top_level.txt
lrn_click/click_ext/__init__.py
lrn_click/click_ext/core.py
lrn_click/click_ext/decorators.py
lrn_click/click_ext/types.py
lrn_click/click_ext/ui.py
lrn_click/utils/__init__.py