Metadata-Version: 1.1
Name: lrn-click
Version: 0.1.5
Summary: Helper Click library to provide enhanced prompts
Home-page: https://github.com/Learnosity/lrn_click
Author: Alan Garfield
Author-email: alan.garfield@learnosity.com
License: UNKNOWN
Download-URL: https://github.com/Learnosity/lrn_click/tarball/0.1.5
Platform: UNKNOWN
